pyscada/__init__.py
pyscada/visa/__init__.py
pyscada/visa/admin.py
pyscada/visa/apps.py
pyscada/visa/device.py
pyscada/visa/models.py
pyscada/visa/signals.py
pyscada/visa/worker.py
pyscada/visa/devices/DS1Z.py
pyscada/visa/devices/HP33120A.py
pyscada/visa/devices/HP3456A.py
pyscada/visa/devices/HP34970A.py
pyscada/visa/devices/HP5342A.py
pyscada/visa/devices/HP54603B.py
pyscada/visa/devices/Keithley_DMM2000.py
pyscada/visa/devices/PI_C-633.py
pyscada/visa/devices/Tektronix_AFG1022.py
pyscada/visa/devices/Tektronix_MDO3014.py
pyscada/visa/devices/__init__.py
pyscada/visa/migrations/0001_initial.py
pyscada/visa/migrations/0002_auto_20161124_1002.py
pyscada/visa/migrations/0003_auto_20170225_0907.py
pyscada/visa/migrations/0004_auto_20170711_1326.py
pyscada/visa/migrations/0005_extendedvisadevice_extendedvisavariable.py
pyscada/visa/migrations/0006_auto_20170905_0942.py
pyscada/visa/migrations/0007_auto_20171219_1327.py
pyscada/visa/migrations/0008_auto_20191004_0912.py
pyscada/visa/migrations/0009_visadevice_instrument_handler.py
pyscada/visa/migrations/0010_devicehandler_migration.py
pyscada/visa/migrations/0011_remove_visadevice_instrument.py
pyscada/visa/migrations/0012_delete_visadevicehandler.py
pyscada/visa/migrations/0013_auto_20220105_1013.py
pyscada/visa/migrations/0014_devicehandler_migration.py
pyscada/visa/migrations/0015_remove_visadevice_instrument_handler.py
pyscada/visa/migrations/0016_alter_visadevice_resource_name.py
pyscada/visa/migrations/0017_add_device_protocol.py
pyscada/visa/migrations/__init__.py
pyscada_visa-0.8.0.dist-info/AUTHORS
pyscada_visa-0.8.0.dist-info/LICENSE
pyscada_visa-0.8.0.dist-info/METADATA
pyscada_visa-0.8.0.dist-info/WHEEL
pyscada_visa-0.8.0.dist-info/top_level.txt
pyscada_visa-0.8.0.dist-info/RECORD
